[
  {
    "name": "Biodance Bio-Collagen Real Deep Mask (10-Pack)",
    "retail": 19.99,
    "landed": 10.30,
    "profit": 8.49,
    "score": 42,
    "url": "https://shop.tiktok.com/us/k/best-selling-sheet-mask"
  },
  {
    "name": "4K Mini Projector WiFi Android 11 Portable Home Theater",
    "retail": 49.99,
    "landed": 34.40,
    "profit": 12.59,
    "score": 5,
    "url": "https://shop.tiktok.com/us/pdp/2026-upgraded-mini-projector-4k-1080p-wifi-6-dual-control/1732051530508309062"
  },
  {
    "name": "4K Mini Projector WiFi Bluetooth 1080P HD 200 ANSI Lumen",
    "retail": 89.99,
    "landed": 60.50,
    "profit": 24.09,
    "score": 29,
    "url": "https://shop.tiktok.com/us/pdp/mini-projector-wifi-bluetooth-1080p-hd-200-ansi-lumen-4k-input/1732086330635948981"
  }
]
